setup.cfg
setup.py
pyverilog_toolbox/__init__.py
pyverilog_toolbox.egg-info/PKG-INFO
pyverilog_toolbox.egg-info/SOURCES.txt
pyverilog_toolbox.egg-info/dependency_links.txt
pyverilog_toolbox.egg-info/top_level.txt
pyverilog_toolbox/gui/__init__.py
pyverilog_toolbox/gui/gui_main.py
pyverilog_toolbox/testcode/case_in_func.v
pyverilog_toolbox/testcode/combloop.v
pyverilog_toolbox/testcode/combloop1.v
pyverilog_toolbox/testcode/combloop2.v
pyverilog_toolbox/testcode/combloop4.v
pyverilog_toolbox/testcode/complex_partselect.v
pyverilog_toolbox/testcode/config_metrics.txt
pyverilog_toolbox/testcode/floating.v
pyverilog_toolbox/testcode/floating2.v
pyverilog_toolbox/testcode/metrics_func.v
pyverilog_toolbox/testcode/metrics_test.v
pyverilog_toolbox/testcode/metrics_test2.v
pyverilog_toolbox/testcode/norm_cnt.v
pyverilog_toolbox/testcode/norm_cnt2.v
pyverilog_toolbox/testcode/norm_cnt3.v
pyverilog_toolbox/testcode/not_combloop.v
pyverilog_toolbox/testcode/out.csv
pyverilog_toolbox/testcode/parser.out
pyverilog_toolbox/testcode/parsetab.py
pyverilog_toolbox/testcode/parsetab.pyc
pyverilog_toolbox/testcode/reg_clone.v
pyverilog_toolbox/testcode/regmap.v
pyverilog_toolbox/testcode/regmap2.v
pyverilog_toolbox/testcode/regmap_split.v
pyverilog_toolbox/testcode/setup.txt
pyverilog_toolbox/testcode/simple.v
pyverilog_toolbox/testcode/test1.v
pyverilog_toolbox/testcode/test2.v
pyverilog_toolbox/testcode/test_ra.py
pyverilog_toolbox/testcode/unreferenced_variables.v
pyverilog_toolbox/verify_tool/__init__.py
pyverilog_toolbox/verify_tool/bindlibrary.py
pyverilog_toolbox/verify_tool/cnt_analyzer.py
pyverilog_toolbox/verify_tool/codeclone_finder.py
pyverilog_toolbox/verify_tool/combloop_finder.py
pyverilog_toolbox/verify_tool/dataflow_facade.py
pyverilog_toolbox/verify_tool/metrics_calculator.py
pyverilog_toolbox/verify_tool/parsetab.py
pyverilog_toolbox/verify_tool/refactor.py
pyverilog_toolbox/verify_tool/regmap_analyzer.py
pyverilog_toolbox/verify_tool/try_simpy.py
pyverilog_toolbox/verify_tool/unreferenced_finder.py