Metadata-Version: 1.0
Name: pyverilog-toolbox
Version: 0.0.5
Summary: Pyverilog-based verification/design tools
Home-page: https://github.com/fukatani/Pyverilog_toolbox
Author: Ryosuke Fukatani
Author-email: nannyakannya@gmail.com
License: Apache License 2.0
Keywords: Verilog,Register Map,code clone,code metrics
Platform: UNKNOWN
